{
    "name": "Iron Shield",
    "icon": "extrastuck:iron_shield",
    "category": "extrastuck:shields",
    "sortnum": 1,
    "pages": [
        {
            "type": "patchouli:spotlight",
            "item": {
                "item": "extrastuck:iron_shield"
            },
            "text": "A reinforced iron shield. That's it."
        },
        {
            "type": "extrastuck:combination",
            "text": "Combine a Shield and an Iron Ingot in a Totem Lathe.",
            "left": "minecraft:shield",
            "mode": "&&",
            "right": "minecraft:iron_ingot",
            "result": "extrastuck:iron_shield"
        }
    ]
}
