{
    "name": "Return to Sender",
    "icon": "extrastuck:return_to_sender",
    "category": "extrastuck:shields",
    "sortnum": 1,
    "pages": [
        {
            "type": "patchouli:spotlight",
            "item": {
                "item": "extrastuck:return_to_sender"
            },
            "text": "An upgraded pogo shield, but you can aim where the projectiles go.$(br)$(br2)$(3)$(l)Special:$() Blocked projectiles bounce back."
        },
        {
            "type": "extrastuck:combination",
            "text": "Combine a Pogo Shield and a Mailbox in a Punch Designix.",
            "left": "extrastuck:pogo_shield",
            "mode": "||",
            "right": "minestuck:mailbox",
            "result": "extrastuck:return_to_sender"
        }
    ]
}
