{
    "name": "Pizza",
    "icon": "extrastuck:pizza",
    "category": "extrastuck:food",
    "pages": [
        {
            "type": "patchouli:spotlight",
            "item": {
                "item": "extrastuck:pizza"
            },
            "text": "A famous dish from a foreign country. Can be placed and eaten in 4 slices that refill 2 hunger."
        },
        {
            "type": "extrastuck:combination",
            "text": "Combine Bread and a Beetroot in a Punch Designix.",
            "left": "minecraft:bread",
            "mode": "||",
            "right": "minecraft:beetroot",
            "result": "extrastuck:pizza"
        },
        {
            "type": "patchouli:spotlight",
            "item": {
                "item": "extrastuck:pizza_slice"
            },
            "text": "A slice of pizza that doesn't need to be placed. Less efficient than a full pizza, but also cheaper and portable."
        },
        {
            "type": "extrastuck:combination",
            "text": "Combine a Pizza and a Dagger in a Punch Designix.",
            "left": "extrastuck:pizza",
            "mode": "||",
            "right": "minestuck:dagger",
            "result": "extrastuck:pizza_slice"
        }
    ]
}
